pedre/__init__.py
pedre/config.py
pedre/constants.py
pedre/helpers.py
pedre/types.py
pedre/view_manager.py
pedre/actions/__init__.py
pedre/actions/base.py
pedre/actions/registry.py
pedre/conditions/__init__.py
pedre/conditions/registry.py
pedre/events/__init__.py
pedre/events/base.py
pedre/events/registry.py
pedre/events/view_events.py
pedre/sprites/__init__.py
pedre/sprites/animated_npc.py
pedre/sprites/animated_player.py
pedre/systems/__init__.py
pedre/systems/base.py
pedre/systems/cache_manager.py
pedre/systems/game_context.py
pedre/systems/loader.py
pedre/systems/registry.py
pedre/systems/audio/__init__.py
pedre/systems/audio/actions.py
pedre/systems/audio/manager.py
pedre/systems/camera/__init__.py
pedre/systems/camera/manager.py
pedre/systems/debug/__init__.py
pedre/systems/debug/manager.py
pedre/systems/dialog/__init__.py
pedre/systems/dialog/actions.py
pedre/systems/dialog/events.py
pedre/systems/dialog/manager.py
pedre/systems/input/__init__.py
pedre/systems/input/manager.py
pedre/systems/interaction/__init__.py
pedre/systems/interaction/conditions.py
pedre/systems/interaction/events.py
pedre/systems/interaction/manager.py
pedre/systems/inventory/__init__.py
pedre/systems/inventory/actions.py
pedre/systems/inventory/conditions.py
pedre/systems/inventory/events.py
pedre/systems/inventory/manager.py
pedre/systems/npc/__init__.py
pedre/systems/npc/actions.py
pedre/systems/npc/conditions.py
pedre/systems/npc/events.py
pedre/systems/npc/manager.py
pedre/systems/particle/__init__.py
pedre/systems/particle/actions.py
pedre/systems/particle/manager.py
pedre/systems/pathfinding/__init__.py
pedre/systems/pathfinding/manager.py
pedre/systems/physics/__init__.py
pedre/systems/physics/manager.py
pedre/systems/player/__init__.py
pedre/systems/player/manager.py
pedre/systems/portal/__init__.py
pedre/systems/portal/events.py
pedre/systems/portal/manager.py
pedre/systems/save/__init__.py
pedre/systems/save/manager.py
pedre/systems/scene/__init__.py
pedre-0.0.7.dist-info/METADATA
pedre-0.0.7.dist-info/WHEEL
pedre-0.0.7.dist-info/licenses/LICENSE
pedre-0.0.7.dist-info/RECORD
