Metadata-Version: 2.4
Name: pedre
Version: 0.0.7
Summary: A Python RPG framework built on Arcade with seamless Tiled map editor integration
Project-URL: Homepage, https://github.com/msaizar/pedre
Project-URL: Repository, https://github.com/msaizar/pedre
Project-URL: Documentation, https://msaizar.github.io/pedre/
Project-URL: Issues, https://github.com/msaizar/pedre/issues
Author-email: Martin Saizar <saizar.martin@gmail.com>
Maintainer-email: Martin Saizar <saizar.martin@gmail.com>
License: BSD-3-Clause
License-File: LICENSE
Keywords: 2d-game,arcade,game,game-engine,game-framework,rpg,tiled,tilemap
Classifier: Development Status :: 3 - Alpha
Classifier: Intended Audience :: Developers
Classifier: License :: OSI Approved :: BSD License
Classifier: Operating System :: OS Independent
Classifier: Programming Language :: Python :: 3
Classifier: Programming Language :: Python :: 3.14
Classifier: Topic :: Games/Entertainment
Classifier: Topic :: Software Development :: Libraries :: Python Modules
Requires-Python: >=3.14
Requires-Dist: arcade
Requires-Dist: rich
